jira_client/__init__.py
jira_client/api_client.py
jira_client/api_response.py
jira_client/configuration.py
jira_client/exceptions.py
jira_client/py.typed
jira_client/rest.py
jira_client/api/__init__.py
jira_client/api/announcement_banner_api.py
jira_client/api/app_data_policies_api.py
jira_client/api/app_migration_api.py
jira_client/api/app_properties_api.py
jira_client/api/application_roles_api.py
jira_client/api/audit_records_api.py
jira_client/api/avatars_api.py
jira_client/api/classification_levels_api.py
jira_client/api/dashboards_api.py
jira_client/api/dynamic_modules_api.py
jira_client/api/filter_sharing_api.py
jira_client/api/filters_api.py
jira_client/api/group_and_user_picker_api.py
jira_client/api/groups_api.py
jira_client/api/issue_attachments_api.py
jira_client/api/issue_bulk_operations_api.py
jira_client/api/issue_comment_properties_api.py
jira_client/api/issue_comments_api.py
jira_client/api/issue_custom_field_associations_api.py
jira_client/api/issue_custom_field_configuration_apps_api.py
jira_client/api/issue_custom_field_contexts_api.py
jira_client/api/issue_custom_field_options_api.py
jira_client/api/issue_custom_field_options_apps_api.py
jira_client/api/issue_custom_field_values_apps_api.py
jira_client/api/issue_field_configurations_api.py
jira_client/api/issue_fields_api.py
jira_client/api/issue_link_types_api.py
jira_client/api/issue_links_api.py
jira_client/api/issue_navigator_settings_api.py
jira_client/api/issue_notification_schemes_api.py
jira_client/api/issue_priorities_api.py
jira_client/api/issue_properties_api.py
jira_client/api/issue_redaction_api.py
jira_client/api/issue_remote_links_api.py
jira_client/api/issue_resolutions_api.py
jira_client/api/issue_search_api.py
jira_client/api/issue_security_level_api.py
jira_client/api/issue_security_schemes_api.py
jira_client/api/issue_type_properties_api.py
jira_client/api/issue_type_schemes_api.py
jira_client/api/issue_type_screen_schemes_api.py
jira_client/api/issue_types_api.py
py_jira_client-0.1.9.dist-info/METADATA
py_jira_client-0.1.9.dist-info/WHEEL
py_jira_client-0.1.9.dist-info/top_level.txt
py_jira_client-0.1.9.dist-info/RECORD
